{
  "orchestrator_id": "01963759-7f8a-74ad-92ce-b40d0643dc93",
  "name": "kairos-orchestrator",
  "mode": "managed-agent",
  "topology_refs": {
    "agents_ref": "../agents/index.json",
    "environments_ref": "../environments/index.json",
    "sessions_ref": "../indexes/sessions.json",
    "live_lane_ref": "../live/live-lane.json"
  },
  "notes": [
    "The orchestrator owns agent session flow and service-mediated workspace mutations.",
    "Execution core remains outside the orchestrator boundary."
  ]
}
